devopsprocessors/__init__.py
devopsprocessors/container.py
devopsprocessors/fluentd/__init__.py
devopsprocessors/fluentd/fluentd_logger.py
devopsprocessors/fluentd/fluentd_processor.py
devopsprocessors/history/__init__.py
devopsprocessors/history/history.py
devopsprocessors/history/history_processor.py
devops_processors-0.0.3.dist-info/LICENSE
devops_processors-0.0.3.dist-info/METADATA
devops_processors-0.0.3.dist-info/WHEEL
devops_processors-0.0.3.dist-info/top_level.txt
devops_processors-0.0.3.dist-info/RECORD
