Metadata-Version: 2.1
Name: devops-processors
Version: 0.0.3
Summary: devops event processors library dist
Home-page: https://github.com/davengeo/devops-processors
Author: David Navarro Alvarez
Author-email: me@davengeo.com
License: UNKNOWN
Platform: UNKNOWN
Classifier: Development Status :: 4 - Beta
Classifier: License :: OSI Approved :: European Union Public Licence 1.2 (EUPL 1.2)
Classifier: Programming Language :: Python :: 3.8
Classifier: Topic :: System :: Systems Administration
License-File: LICENSE
Requires-Dist: cloudevents
Requires-Dist: dependency-injector (<5.0,>=4.0)
Requires-Dist: fluent-logger
Requires-Dist: prometheus-client
